{
    "allow_forward_starting": 0,
    "delay_amount": 0,
    "display_name": "AUD Basket",
    "display_order": 23,
    "exchange_is_open": 1,
    "exchange_name": "FOREX",
    "intraday_interval_minutes": 5,
    "is_trading_suspended": 0,
    "market": "synthetic_index",
    "market_display_name": "Derived",
    "pip": 0.001,
    "quoted_currency_symbol": "WLDAUD",
    "spot": 920.717,
    "spot_age": "0",
    "spot_percentage_change": "0.00",
    "spot_time": "1675855084",
    "subgroup": "baskets",
    "subgroup_display_name": "Baskets",
    "submarket": "forex_basket",
    "submarket_display_name": "Forex Basket",
    "symbol": "WLDAUD",
    "symbol_type": "forex_basket"
}